moons/__init__.py
moons/admin.py
moons/api.py
moons/app_settings.py
moons/apps.py
moons/auth_hooks.py
moons/helpers.py
moons/managers.py
moons/models.py
moons/mooncogs.py
moons/providers.py
moons/schema.py
moons/tasks.py
moons/urls.py
moons/views.py
moons/locale/de/LC_MESSAGES/django.po
moons/locale/en/LC_MESSAGES/django.po
moons/management/commands/__init__.py
moons/management/commands/moons_fix_null_moons.py
moons/management/commands/moons_load_moons.py
moons/management/commands/moons_setup_tool.py
moons/management/commands/moons_tax_outstanding.py
moons/management/commands/moons_update_prices.py
moons/migrations/0001_initial.py
moons/migrations/0002_auto_20201128_1356.py
moons/migrations/0003_auto_20201205_0606.py
moons/migrations/0004_auto_20201205_0626.py
moons/migrations/0005_remove_miningobservation_frack.py
moons/migrations/0006_miningobservation_structure.py
moons/migrations/0007_miningtax_oreprice_oretax_oretaxrates.py
moons/migrations/0008_auto_20210827_1015.py
moons/migrations/0009_alter_miningtax_flat_tax_rate.py
moons/migrations/0010_miningobservation_moon.py
moons/migrations/0011_oretax_tax.py
moons/migrations/0012_rename_excptional_rate_oretaxrates_exceptional_rate.py
moons/migrations/0013_auto_20210904_0948.py
moons/migrations/0014_invoicerecord_tax_dump.py
moons/migrations/0015_auto_20210906_0915.py
moons/migrations/0016_invoicerecord_base_ref.py
moons/migrations/0017_moonrental.py
moons/migrations/0018_alter_moonfrack_options.py
moons/migrations/0019_oreprice_goo_only_oretaxrates_ignore_ores_in_refine.py
moons/migrations/0020_alter_moonrental_price.py
moons/migrations/__init__.py
moons/static/moons/manifest.json
moons/static/moons/assets/@libs-B9yFRFlX.js
moons/static/moons/assets/@libs-B9yFRFlX.js.map
moons/static/moons/assets/@react-router-BkR6W0qd.js
moons/static/moons/assets/@react-router-BkR6W0qd.js.map
moons/static/moons/assets/index-duNaZmUg.js
moons/static/moons/assets/index-duNaZmUg.js.map
moons/static/moons/css/index-BTQ8LwxG.css
allianceauth_corptools_moons-1.0.1.dist-info/METADATA
allianceauth_corptools_moons-1.0.1.dist-info/WHEEL
allianceauth_corptools_moons-1.0.1.dist-info/licenses/LICENSE
allianceauth_corptools_moons-1.0.1.dist-info/RECORD
