Metadata-Version: 2.4
Name: allianceauth-corptools-moons
Version: 1.0.1
Dynamic: Summary
Project-URL: Homepage, https://github.com/Solar-Helix-Independent-Transport/allianceauth-corp-tools-moons
Project-URL: Source, https://github.com/Solar-Helix-Independent-Transport/allianceauth-corp-tools-moons
Project-URL: Tracker, https://github.com/Solar-Helix-Independent-Transport/allianceauth-corp-tools-moons/issues
Author-email: AaronKable <aaronkable@gmail.com>
License: Copyright (c) 2023 Aaron Kable
License-File: LICENSE
Classifier: Environment :: Web Environment
Classifier: Framework :: Celery
Classifier: Framework :: Django
Classifier: Framework :: Django :: 4.0
Classifier: Framework :: Django :: 4.2
Classifier: Intended Audience :: Developers
Classifier: License :: OSI Approved :: MIT License
Classifier: Operating System :: OS Independent
Classifier: Programming Language :: Python
Classifier: Programming Language :: Python :: 3 :: Only
Classifier: Programming Language :: Python :: 3.10
Classifier: Programming Language :: Python :: 3.11
Classifier: Programming Language :: Python :: 3.12
Classifier: Programming Language :: Python :: Implementation :: CPython
Classifier: Topic :: Internet :: WWW/HTTP
Classifier: Topic :: Internet :: WWW/HTTP :: Dynamic Content
Requires-Python: >=3.10
Requires-Dist: allianceauth-corptools>=2.5.5
Requires-Dist: allianceauth-invoices>=0.1.1
Requires-Dist: allianceauth>=4
Requires-Dist: django-ninja<2,>=1.0.1
